CHANGELOG.md
LICENSE
MANIFEST.in
README.md
requirements.txt
setup.py
octobot_script/__init__.py
octobot_script/cli.py
octobot_script/constants.py
octobot_script.egg-info/PKG-INFO
octobot_script.egg-info/SOURCES.txt
octobot_script.egg-info/dependency_links.txt
octobot_script.egg-info/entry_points.txt
octobot_script.egg-info/not-zip-safe
octobot_script.egg-info/requires.txt
octobot_script.egg-info/top_level.txt
octobot_script/ai/__init__.py
octobot_script/ai/agents.py
octobot_script/ai/environments.py
octobot_script/ai/models.py
octobot_script/api/__init__.py
octobot_script/api/data_fetching.py
octobot_script/api/execution.py
octobot_script/api/ploting.py
octobot_script/config/config_mock.json
octobot_script/config/logging_config.ini
octobot_script/internal/__init__.py
octobot_script/internal/backtester_trading_mode.py
octobot_script/internal/logging_util.py
octobot_script/internal/octobot_mocks.py
octobot_script/internal/runners.py
octobot_script/model/__init__.py
octobot_script/model/backtest_plot.py
octobot_script/model/backtest_result.py
octobot_script/model/errors.py
octobot_script/model/strategy.py
octobot_script/resources/__init__.py
octobot_script/resources/reports/default_report_template.html
octobot_script/resources/reports/header.html
octobot_script/resources/reports/scripts.html
octobot_script/resources/reports/css/style.css
octobot_script/resources/reports/css/w2ui_template.css
octobot_script/resources/reports/js/common.js
octobot_script/resources/reports/js/data.js
octobot_script/resources/reports/js/graphs.js
octobot_script/resources/reports/js/tables.js
octobot_script/resources/reports/js/texts.js
tests/api/__init__.py
tests/api/test_data_fetching.py
tests/api/test_execution.py
tests/functionnal/__init__.py
tests/functionnal/example_scripts/__init__.py
tests/functionnal/example_scripts/test_precomputed_vs_iteration_rsi.py