Metadata-Version: 2.4
Name: octobot_script
Version: 0.0.29
Summary: Backtesting framework of the OctoBot Ecosystem
Home-page: https://github.com/Drakkar-Software/OctoBot-Script
Author: Drakkar-Software
Author-email: contact@drakkar.software
License: GPL-3.0
Classifier: Development Status :: 5 - Production/Stable
Classifier: Operating System :: OS Independent
Classifier: Operating System :: MacOS :: MacOS X
Classifier: Operating System :: Microsoft :: Windows
Classifier: Operating System :: POSIX
Classifier: Programming Language :: Python :: 3.10
Requires-Python: >=3.8
License-File: LICENSE
Requires-Dist: OctoBot[full]==2.0.16
Requires-Dist: appdirs==1.4.4
Requires-Dist: click==8.1.3
Requires-Dist: jinja2
Requires-Dist: aiohttp
Requires-Dist: wheel
Dynamic: author
Dynamic: author-email
Dynamic: classifier
Dynamic: description
Dynamic: description-content-type
Dynamic: home-page
Dynamic: license
Dynamic: license-file
Dynamic: requires-dist
Dynamic: requires-python
Dynamic: summary
